DS_Students/MultipleChoices.py
DS_Students/__init__.py
DS_Students-0.1.5.dist-info/LICENSE
DS_Students-0.1.5.dist-info/METADATA
DS_Students-0.1.5.dist-info/WHEEL
DS_Students-0.1.5.dist-info/top_level.txt
DS_Students-0.1.5.dist-info/RECORD
