Metadata-Version: 2.1
Name: DS-Students
Version: 0.1.5
Summary: Python package for Data Science Students
Home-page: https://github.com/woz-u/DS-Student-Resources
Author: Matthew Gerardino
Author-email: matthewgerardino@gmail.com
License: MIT License
Platform: UNKNOWN
License-File: LICENSE
Requires-Dist: ipywidgets
Requires-Dist: ipynb
Requires-Dist: ipython
